stock_pair_cointegration/__init__.py
stock_pair_cointegration/figure_to_svg_string.py
stock_pair_cointegration/main.py
stock_pair_cointegration/pair_cointegration.py
stocks_pair_cointegration-0.0.1.dist-info/METADATA
stocks_pair_cointegration-0.0.1.dist-info/WHEEL
stocks_pair_cointegration-0.0.1.dist-info/RECORD
