Metadata-Version: 2.1
Name: stocks-pair-cointegration
Version: 0.0.1
Summary: Get the cointegration result of a pair of stocks.
Author: tim-hub
Author-email: tim-hub@users.noreply.github.com
Requires-Python: >=3.12,<4.0
Classifier: Programming Language :: Python :: 3
Classifier: Programming Language :: Python :: 3.12
Requires-Dist: arch (>=7.2.0,<8.0.0)
Requires-Dist: asyncio (>=3.4.3,<4.0.0)
Requires-Dist: matplotlib (>=3.9.3,<4.0.0)
Requires-Dist: numpy (>=2.2.0,<3.0.0)
Requires-Dist: pandas (>=2.2.3,<3.0.0)
